src/__init__.py
src/read/__init__.py
src/read/interaction/Interaction.py
src/read/interaction/SimpleInteraction.py
src/read/interaction/__init__.py
src/read/interaction/displayable/__init__.py
src/read/interaction/interpreter/Interpreter.py
src/read/interaction/interpreter/OptionInterpreter.py
src/read/interaction/interpreter/__init__.py
src/read/interaction/prompt/InterpChainPrompt.py
src/read/interaction/prompt/Prompt.py
src/read/interaction/prompt/__init__.py
src/read/story/SimpleGraphStory.py
src/read/story/Story.py
src/read/story/StringBuilderStory.py
src/read/story/__init__.py
src/read/story/graph/GraphStoryModel.py
src/read/story/graph/Paragraph.py
src/read/story/graph/Phrase.py
src/read/story/graph/__init__.py
src/read/storyteller/SimpleStoryteller.py
src/read/storyteller/Storyteller.py
src/read/storyteller/__init__.py
src/read/view/StringOptionView.py
src/read/view/View.py
src/read/view/__init__.py
src/write/__init__.py
src/write/draft/Draft.py
src/write/draft/__init__.py
src/write/editor/Editor.py
src/write/editor/__init__.py
src/write/environment/Environment.py
src/write/environment/__init__.py
src/write/environment/scale/SCALE.py
src/write/environment/scale/__init__.py
src/write/environment/scale/scale_main.py
solaria-0.0.0.dist-info/LICENSE
solaria-0.0.0.dist-info/METADATA
solaria-0.0.0.dist-info/WHEEL
solaria-0.0.0.dist-info/top_level.txt
solaria-0.0.0.dist-info/RECORD
