Metadata-Version: 2.1
Name: solaria
Version: 0.0.0
Summary: An API for interactive storytelling.
Home-page: UNKNOWN
Author: Casey Pancoast
Author-email: cqpancoast@gmail.com
License: UNKNOWN
Platform: UNKNOWN
Classifier: Programming Language :: Python
Classifier: License :: OSI Approved :: MIT License
Classifier: Operating System :: OS Independent
